[{"id":"120","image": "https://muqp.ml/C0wUqEdZD0mubcom","desc":"BFM V","year":"NOV 2019","name":"Business Ethics and Corporate Governance"},{"id":"125","image": "https://muqp.ml/wtTXJbD9XNmubcom","desc":"BFM V","year":"NOV 2019","name":"Business Valuation"},{"id":"119","image": "https://muqp.ml/BBqrvcX6Ummubcom","desc":"BFM V","year":"NOV 2019","name":"Corporate Accounting"},{"id":"124","image": "https://muqp.ml/Wxt3yUe6BKmubcom","desc":"BFM V","year":"NOV 2019","name":"Direct Tax-Indirect Tax"},{"id":"122","image": "https://muqp.ml/hc4RfaEO1Kmubcom","desc":"BFM V","year":"NOV 2019","name":"Equity Research"},{"id":"117","image": "https://muqp.ml/KQmqzhntR9mubcom","desc":"BFM V","year":"NOV 2019","name":"Financial Derivatives"},{"id":"116","image": "https://muqp.ml/ecnfG9wJv5mubcom","desc":"BFM V","year":"NOV 2019","name":"Marketing in Financial Services"},{"id":"121","image": "https://muqp.ml/nPOGmQAZ3Emubcom","desc":"BFM V","year":"NOV 2019","name":"Technical Analysis"}]